{"cZzYQULkET8buxuK7TbrPw==":"2020-06-13_22.10.25-2000x1059.png","JULNzXkmKqSWrv+yaefkEQ==":"4funsv-logo-project-121x67.png","53nZXUsoFgXGKFLHEhQnTQ==":"logoaquatic-219x219.png","CZsJMQ6TWmShrHGDn+Hn0g==":"2018-08-17_16.54.46-2000x1993.png","F41RqGExmhkFqYCqji/aGQ==":"mbr-1920x1357.jpg","nVs23oFGFz/ohlk5kJoLTg==":"2019-04-21_19.29.55-2000x1175.png","QuKcjUQ90jux8LRV5NgjEQ==":"2019-04-21_19.29.55-1-2000x1175.png","6uOVUm1sVbLcSlAtwXJu8g==":"alphacraft-banner1600-948x237.png","lwAideJOri8UOymqcIdnWQ==":"bez%C2%A0tytu%C5%82u-570x361.png","h12Q+nZ1Fnwb4K9iS45NzQ==":"dphz-sv_big-761x222.png","hXNZo2KwgmnnDjSYbePipg==":"logo-800x240.png","/Wl1/YWt4UDDKCmSattDtA==":"smile-900x900.png","aieY3QNoeNCC6NNQyfCwpA==":"smile-1-900x900.png","G6ohFUAZdAgzrU2oJEZalQ==":"4fun-cuboids-logo-948x948.png","QmT2BwKr4UKT/NDy31+5hw==":"4fun-survival-948x749.png","mS5WLwIejTb6WXEDZ8ITag==":"matesurvival-roundlogo-948x948.png","1bCjp77pu/E0/kVlqGXOMw==":"server-icon-64x64.png","SRtfaEPErLAPgTfu7GMF6Q==":"server-icon-1-64x64.png","JN4mFEUtC/kOlgwxwM+VDA==":"logo-1-800x240.png","YH8TAYnkIsaDkMZsGoBLCA==":"3edycja-948x319.jpg","l2FtPxre13G7ggvshz2Mug==":"background3.jpeg","iab3X2JfZwPG3uTWyrBGHw==":"manifest-541x251.jpg","2V3Uf6QZQf6y5oNrFiAP6Q==":"4fun-cuboids-logo-121x121.png","138vxaVtZxApBKHcow8iNw==":"tlo-1920x1017.jpg","WM989nEAOw8JMhc6RlUQqA==":"tlo2-1762x1306.jpg","r4raF+w4wcHQBdFKLNZaAQ==":"4funcubs-prezkav5-1600x5282.jpg","rfRh2EhfGwQIzgX9IvM7Ww==":"4funsv-logo-round-860x860.png"}